ospd/__init__.py
ospd/command/__init__.py
ospd/command/command.py
ospd/command/initsubclass.py
ospd/command/registry.py
ospd/config.py
ospd/cvss.py
ospd/datapickler.py
ospd/errors.py
ospd/logger.py
ospd/main.py
ospd/misc.py
ospd/network.py
ospd/ospd.py
ospd/parser.py
ospd/protocol.py
ospd/resultlist.py
ospd/scan.py
ospd/server.py
ospd/timer.py
ospd/vtfilter.py
ospd/vts.py
ospd/xml.py
ospd/xmlvt.py
ospd_openvas/__init__.py
ospd_openvas/__version__.py
ospd_openvas/daemon.py
ospd_openvas/db.py
ospd_openvas/dryrun.py
ospd_openvas/errors.py
ospd_openvas/gpg_sha_verifier.py
ospd_openvas/lock.py
ospd_openvas/messages/__init__.py
ospd_openvas/messages/message.py
ospd_openvas/messages/result.py
ospd_openvas/messaging/__init__.py
ospd_openvas/messaging/mqtt.py
ospd_openvas/messaging/publisher.py
ospd_openvas/messaging/subscriber.py
ospd_openvas/notus.py
ospd_openvas/nvticache.py
ospd_openvas/openvas.py
ospd_openvas/preferencehandler.py
ospd_openvas/vthelper.py
ospd_openvas-22.10.1.dist-info/METADATA
ospd_openvas-22.10.1.dist-info/WHEEL
ospd_openvas-22.10.1.dist-info/entry_points.txt
ospd_openvas-22.10.1.dist-info/licenses/COPYING
ospd_openvas-22.10.1.dist-info/RECORD
