Metadata-Version: 2.4
Name: ospd-openvas
Version: 22.10.1
Summary: ospd based scanner for openvas
License: AGPL-3.0-or-later
License-File: COPYING
Keywords: openvas,Greenbone Vulnerability Management,Vulnerability Scanning,OSP,Open Scanner Protocol
Author: Greenbone AG
Author-email: info@greenbone.net
Requires-Python: >=3.9,<4.0
Classifier: Development Status :: 4 - Beta
Classifier: Intended Audience :: Developers
Classifier: Intended Audience :: System Administrators
Classifier: License :: OSI Approved :: GNU Affero General Public License v3 or later (AGPLv3+)
Classifier: Programming Language :: Python :: 3
Classifier: Programming Language :: Python :: 3.9
Classifier: Programming Language :: Python :: 3.10
Classifier: Programming Language :: Python :: 3.11
Classifier: Programming Language :: Python :: 3.12
Classifier: Programming Language :: Python :: 3.13
Classifier: Programming Language :: Python :: 3.14
Requires-Dist: defusedxml (>=0.6,<0.8)
Requires-Dist: deprecated (>=1.2.10,<2.0.0)
Requires-Dist: lxml (>=4.5.2,<7.0.0)
Requires-Dist: packaging (>=20.4,<27.0)
Requires-Dist: paho-mqtt (>=1.6,<3)
Requires-Dist: psutil (>=5.5.1,<8.0.0)
Requires-Dist: python-gnupg (>=0.4.8,<0.6.0)
Requires-Dist: redis (>=4.5.0)
Project-URL: Homepage, https://github.com/greenbone/ospd-openvas
Project-URL: Repository, https://github.com/greenbone/ospd-openvas
